{
   "nodes": 
[{"index":0,"id":307,"name":"Current_clamp","group":0,"x":745.4,"y":445.2,"keywords":"clamp,meter,current,conductor,vane"},{"index":1,"id":446,"name":"Bus_duct","group":0,"x":588.1,"y":431.6,"keywords":"duct,bu,firestop,busbar,test"},{"index":2,"id":479,"name":"Battery_room","group":0,"x":574.1,"y":444.2,"keywords":"battery,batterie,room,acid,power"},{"index":3,"id":630,"name":"Distribution_board","group":0,"x":574.7,"y":417.1,"keywords":"breaker,panel,fuse,board,cu"},{"index":4,"id":664,"name":"Eaton_Corporation","group":0,"x":701.9,"y":470.7,"keywords":"eaton,company,cooper,acquisition,powerware"},{"index":5,"id":816,"name":"Three-phase","group":0,"x":699.5,"y":435.8,"keywords":"phase,neutral,current,balanced,load"},{"index":6,"id":839,"name":"Busbar","group":0,"x":558.5,"y":410.5,"keywords":"busbar,bu,busway,millimetre,duct"},{"index":7,"id":1037,"name":"CHAdeMO","group":0,"x":662.6,"y":475.8,"keywords":"chademo,charging,charger,dc,fast"},{"index":8,"id":1670,"name":"Eaton_BladeUPS","group":0,"x":758,"y":503.4,"keywords":"bladeup,eaton,runtime,software,online"},{"index":9,"id":1838,"name":"Wall_socket","group":0,"x":611.6,"y":517.2,"keywords":"socket,plug,cee,adaptor,receptacle"},{"index":10,"id":1896,"name":"AC_power_plugs_and_sockets","group":0,"x":620,"y":543.1,"keywords":"socket,plug,cee,receptacle,adaptor"},{"index":11,"id":2198,"name":"Perilex","group":0,"x":666.6,"y":566.6,"keywords":"connector,perilex,din,germany,ampere"},{"index":12,"id":2209,"name":"Industrial_and_multiphase_power_plugs_and_sockets","group":0,"x":708,"y":521.1,"keywords":"plug,connector,phase,pin,socket"},{"index":13,"id":2227,"name":"Portable_cord","group":0,"x":687.3,"y":450.3,"keywords":"cord,portable,thermoplastic,jacket,resistant"},{"index":14,"id":2594,"name":"Electrical_wiring","group":0,"x":676,"y":401.1,"keywords":"wiring,cable,conductor,wire,code"},{"index":15,"id":2631,"name":"Thermoplastic-sheathed_cable","group":0,"x":659.5,"y":367.5,"keywords":"conductor,cable,wire,sheath,gauge"},{"index":16,"id":2685,"name":"Electrical_wiring_in_North_America","group":0,"x":648,"y":412.8,"keywords":"wiring,wire,neutral,conductor,code"},{"index":17,"id":2954,"name":"Scott-T_transformer","group":0,"x":705.1,"y":434.1,"keywords":"phase,scott,transformer,load,balanced"},{"index":18,"id":2989,"name":"Power_cable","group":0,"x":646.2,"y":424.3,"keywords":"cable,conductor,flexible,sheath,insulated"},{"index":19,"id":3154,"name":"IEC_62196","group":0,"x":659.2,"y":509.9,"keywords":"charging,iec,plug,connector,mode"},{"index":20,"id":3262,"name":"Copper_wire_and_cable","group":0,"x":549.4,"y":395.4,"keywords":"copper,wire,cable,electrical,conductivity"},{"index":21,"id":3323,"name":"Type_2_connector","group":0,"x":627.3,"y":500.9,"keywords":"vehicle,charging,pin,connector,menneke"},{"index":22,"id":3506,"name":"Electrical_room","group":0,"x":608.9,"y":401.3,"keywords":"room,electrical,equipment,regulation,building"},{"index":23,"id":3570,"name":"Instrument_transformer","group":0,"x":733.3,"y":410.5,"keywords":"transformer,secondary,ct,pt,voltage"},{"index":24,"id":3661,"name":"Europlug","group":0,"x":628.7,"y":542.2,"keywords":"europlug,socket,plug,uk,pin"},{"index":25,"id":4013,"name":"Electrical_wiring_in_the_United_Kingdom","group":0,"x":634.6,"y":455.4,"keywords":"wiring,colour,regulation,socket,circuit"},{"index":26,"id":4111,"name":"Insulated_Cable_Engineers_Association","group":0,"x":627.7,"y":399.8,"keywords":"association,cable,insulated,icea,engineer"},{"index":27,"id":4233,"name":"Single-phase_electric_power","group":0,"x":590.5,"y":486.1,"keywords":"phase,single,distribution,motor,neutral"},{"index":28,"id":4243,"name":"SAE_J1772","group":0,"x":626.9,"y":481.9,"keywords":"sae,charging,vehicle,connector,pin"},{"index":29,"id":4802,"name":"Emergency_power_system","group":0,"x":577,"y":500.6,"keywords":"emergency,power,standby,batterie,los"},{"index":30,"id":4872,"name":"NEMA_connector","group":0,"x":571.1,"y":518,"keywords":"nema,receptacle,plug,blade,connector"},{"index":31,"id":4903,"name":"GOST_7396","group":0,"x":582.6,"y":540.2,"keywords":"plug,socket,schuko,cee,standard"},{"index":32,"id":4942,"name":"Split-phase_electric_power","group":0,"x":601.9,"y":465.3,"keywords":"phase,neutral,conductor,wire,single"},{"index":33,"id":5060,"name":"Socapex","group":0,"x":697.5,"y":540.9,"keywords":"socapex,connector,breakout,pin,fixture"},{"index":34,"id":5211,"name":"MIL-DTL-13486","group":0,"x":710.4,"y":396,"keywords":"mil,wire,dtl,spec,defense"},{"index":35,"id":5245,"name":"IEC_60309","group":0,"x":648.4,"y":540.2,"keywords":"colour,plug,socket,fitting,blue"},{"index":36,"id":5327,"name":"Backup_battery","group":0,"x":582.9,"y":415.8,"keywords":"backup,battery,batterie,power,vrla"},{"index":37,"id":5349,"name":"Stage_pin_connector","group":0,"x":670.4,"y":513.8,"keywords":"connector,pin,stage,cable,edison"}]
, 
"links": 
[{"source":0,"target":5,"value":2},{"source":1,"target":6,"value":2},{"source":1,"target":18,"value":2},{"source":3,"target":27,"value":2},{"source":3,"target":6,"value":2},{"source":4,"target":8,"value":2},{"source":5,"target":17,"value":2},{"source":6,"target":3,"value":2},{"source":6,"target":1,"value":2},{"source":7,"target":19,"value":2},{"source":7,"target":28,"value":2},{"source":7,"target":4,"value":2},{"source":8,"target":4,"value":2},{"source":9,"target":19,"value":2},{"source":9,"target":29,"value":2},{"source":9,"target":31,"value":2},{"source":9,"target":28,"value":2},{"source":9,"target":27,"value":2},{"source":9,"target":24,"value":2},{"source":9,"target":21,"value":2},{"source":9,"target":35,"value":2},{"source":9,"target":30,"value":2},{"source":9,"target":37,"value":2},{"source":10,"target":19,"value":2},{"source":10,"target":29,"value":2},{"source":10,"target":31,"value":2},{"source":10,"target":28,"value":2},{"source":10,"target":27,"value":2},{"source":10,"target":24,"value":2},{"source":10,"target":21,"value":2},{"source":10,"target":35,"value":2},{"source":10,"target":30,"value":2},{"source":10,"target":37,"value":2},{"source":11,"target":35,"value":2},{"source":12,"target":37,"value":2},{"source":12,"target":35,"value":2},{"source":12,"target":10,"value":2},{"source":12,"target":5,"value":2},{"source":12,"target":24,"value":2},{"source":12,"target":33,"value":2},{"source":13,"target":18,"value":2},{"source":13,"target":14,"value":2},{"source":14,"target":34,"value":2},{"source":14,"target":27,"value":2},{"source":14,"target":16,"value":2},{"source":14,"target":3,"value":2},{"source":14,"target":12,"value":2},{"source":14,"target":13,"value":2},{"source":14,"target":18,"value":2},{"source":14,"target":22,"value":2},{"source":14,"target":25,"value":2},{"source":14,"target":15,"value":2},{"source":15,"target":16,"value":2},{"source":15,"target":14,"value":2},{"source":16,"target":5,"value":2},{"source":16,"target":26,"value":2},{"source":16,"target":25,"value":2},{"source":16,"target":18,"value":2},{"source":16,"target":14,"value":2},{"source":16,"target":32,"value":2},{"source":17,"target":27,"value":2},{"source":17,"target":5,"value":2},{"source":18,"target":13,"value":2},{"source":18,"target":10,"value":2},{"source":18,"target":14,"value":2},{"source":18,"target":20,"value":2},{"source":18,"target":12,"value":2},{"source":18,"target":15,"value":2},{"source":19,"target":35,"value":2},{"source":19,"target":7,"value":2},{"source":19,"target":12,"value":2},{"source":19,"target":28,"value":2},{"source":19,"target":21,"value":2},{"source":20,"target":6,"value":2},{"source":20,"target":14,"value":2},{"source":21,"target":27,"value":2},{"source":21,"target":35,"value":2},{"source":21,"target":19,"value":2},{"source":21,"target":28,"value":2},{"source":21,"target":7,"value":2},{"source":22,"target":6,"value":2},{"source":22,"target":2,"value":2},{"source":22,"target":3,"value":2},{"source":22,"target":36,"value":2},{"source":23,"target":0,"value":2},{"source":24,"target":10,"value":2},{"source":25,"target":16,"value":2},{"source":25,"target":27,"value":2},{"source":25,"target":3,"value":2},{"source":25,"target":35,"value":2},{"source":25,"target":5,"value":2},{"source":26,"target":18,"value":2},{"source":27,"target":5,"value":2},{"source":27,"target":32,"value":2},{"source":28,"target":27,"value":2},{"source":28,"target":7,"value":2},{"source":28,"target":19,"value":2},{"source":28,"target":32,"value":2},{"source":29,"target":2,"value":2},{"source":30,"target":10,"value":2},{"source":30,"target":32,"value":2},{"source":31,"target":30,"value":2},{"source":31,"target":24,"value":2},{"source":32,"target":27,"value":2},{"source":33,"target":35,"value":2},{"source":33,"target":37,"value":2},{"source":34,"target":14,"value":2},{"source":35,"target":10,"value":2},{"source":35,"target":24,"value":2},{"source":35,"target":12,"value":2},{"source":35,"target":11,"value":2},{"source":35,"target":32,"value":2},{"source":36,"target":2,"value":2},{"source":37,"target":13,"value":2},{"source":37,"target":35,"value":2},{"source":37,"target":33,"value":2}]
}