{
   "nodes": 
[{"index":0,"id":28,"name":"Reynolds_number","group":0,"x":686.1,"y":387.1,"keywords":"reynold,fluid,flow,osborne,popularized"},{"index":1,"id":459,"name":"Harmonic_oscillator","group":0,"x":705.7,"y":506.7,"keywords":"oscillator,harmonic,force,damped,driving"},{"index":2,"id":2189,"name":"Central_force","group":0,"x":655.7,"y":529.6,"keywords":"force,central,field,conservative,origin"},{"index":3,"id":2264,"name":"Mechanical_advantage","group":0,"x":611.5,"y":487.6,"keywords":"gear,force,mechanical,advantage,input"},{"index":4,"id":3869,"name":"Drag_coefficient","group":0,"x":623.9,"y":406.7,"keywords":"drag,coefficient,fluid,effect,object"},{"index":5,"id":4808,"name":"Angular_frequency","group":0,"x":694.6,"y":498.1,"keywords":"angular,frequency,rate,radian,quantity"},{"index":6,"id":4819,"name":"Moment_of_inertia","group":0,"x":619.8,"y":478.6,"keywords":"inertia,moment,body,axi,torque"},{"index":7,"id":6818,"name":"Andr%C3%A9-Marie_Amp%C3%A8re","group":0,"x":616.2,"y":460.5,"keywords":"ampre,online,google,marie,andr"},{"index":8,"id":8026,"name":"Crystallization","group":0,"x":703.8,"y":439.5,"keywords":"crystal,crystallization,nucleation,crystallizer,solute"},{"index":9,"id":8931,"name":"Jerk_(physics)","group":0,"x":662.2,"y":442.3,"keywords":"jerk,acceleration,force,derivative,angular"},{"index":10,"id":9037,"name":"Dipole","group":0,"x":667.9,"y":518.7,"keywords":"dipole,electric,charge,current,electret"},{"index":11,"id":9172,"name":"Gear","group":0,"x":673.9,"y":495.1,"keywords":"gear,pitch,tooth,teeth,helical"},{"index":12,"id":9960,"name":"SI_base_unit","group":0,"x":680.9,"y":461.1,"keywords":"mole,si,kilogram,cgpm,unit"},{"index":13,"id":10548,"name":"Hamiltonian_system","group":0,"x":724.1,"y":518.3,"keywords":"hamiltonian,dynamical,evolution,liouville,hamilton"},{"index":14,"id":10703,"name":"Pseudovector","group":0,"x":605.8,"y":435.5,"keywords":"pseudovector,vector,polar,rotation,product"},{"index":15,"id":14177,"name":"Rotation","group":0,"x":554.7,"y":444.5,"keywords":"rotation,axi,planet,body,spin"},{"index":16,"id":14323,"name":"Rigid_body_dynamics","group":0,"x":572.5,"y":479.4,"keywords":"rigid,bodie,body,force,action"},{"index":17,"id":14669,"name":"Right-hand_rule","group":0,"x":565.4,"y":442.2,"keywords":"magnetic,finger,thumb,rule,direction"},{"index":18,"id":15627,"name":"Torque","group":0,"x":629.8,"y":486.9,"keywords":"torque,force,angular,speed,moment"},{"index":19,"id":16286,"name":"Resonance","group":0,"x":608.4,"y":468.3,"keywords":"resonance,resonant,frequency,swing,frequencie"},{"index":20,"id":17919,"name":"Inductance","group":0,"x":714.6,"y":510.2,"keywords":"inductance,inductor,circuit,current,mutual"},{"index":21,"id":18422,"name":"Wheeler%E2%80%93Feynman_absorber_theory","group":0,"x":641.7,"y":489.7,"keywords":"absorber,particle,wave,interpretation,causality"},{"index":22,"id":18526,"name":"Screw_axis","group":0,"x":600,"y":400.1,"keywords":"axi,screw,displacement,rotation,chasle"},{"index":23,"id":19665,"name":"Degrees_of_freedom_(physics_and_chemistry)","group":0,"x":662.5,"y":396.2,"keywords":"freedom,degree,molecule,quadratic,energy"},{"index":24,"id":22689,"name":"Kinematic_pair","group":0,"x":729.4,"y":492.6,"keywords":"joint,body,pair,contact,moving"},{"index":25,"id":23064,"name":"Angular_velocity","group":0,"x":618.1,"y":435.1,"keywords":"angular,velocity,frame,rotation,vector"},{"index":26,"id":23669,"name":"Dimensional_analysis","group":0,"x":686.5,"y":503.2,"keywords":"v,unit,analysi,dimensional,kilogram"}]
, 
"links": 
[{"source":0,"target":4,"value":2},{"source":0,"target":25,"value":2},{"source":1,"target":6,"value":2},{"source":1,"target":20,"value":2},{"source":1,"target":25,"value":2},{"source":1,"target":19,"value":2},{"source":1,"target":18,"value":2},{"source":1,"target":5,"value":2},{"source":2,"target":1,"value":2},{"source":2,"target":18,"value":2},{"source":4,"target":0,"value":2},{"source":5,"target":1,"value":2},{"source":5,"target":26,"value":2},{"source":5,"target":20,"value":2},{"source":5,"target":25,"value":2},{"source":6,"target":16,"value":2},{"source":6,"target":19,"value":2},{"source":6,"target":25,"value":2},{"source":6,"target":18,"value":2},{"source":6,"target":5,"value":2},{"source":8,"target":0,"value":2},{"source":9,"target":26,"value":2},{"source":9,"target":12,"value":2},{"source":9,"target":21,"value":2},{"source":9,"target":0,"value":2},{"source":9,"target":6,"value":2},{"source":9,"target":4,"value":2},{"source":9,"target":25,"value":2},{"source":9,"target":19,"value":2},{"source":9,"target":18,"value":2},{"source":9,"target":14,"value":2},{"source":10,"target":18,"value":2},{"source":10,"target":5,"value":2},{"source":11,"target":3,"value":2},{"source":11,"target":18,"value":2},{"source":11,"target":5,"value":2},{"source":12,"target":7,"value":2},{"source":12,"target":26,"value":2},{"source":13,"target":1,"value":2},{"source":14,"target":25,"value":2},{"source":14,"target":18,"value":2},{"source":14,"target":17,"value":2},{"source":15,"target":6,"value":2},{"source":15,"target":25,"value":2},{"source":15,"target":18,"value":2},{"source":15,"target":5,"value":2},{"source":15,"target":17,"value":2},{"source":16,"target":6,"value":2},{"source":16,"target":18,"value":2},{"source":16,"target":14,"value":2},{"source":16,"target":17,"value":2},{"source":17,"target":7,"value":2},{"source":17,"target":18,"value":2},{"source":17,"target":14,"value":2},{"source":17,"target":25,"value":2},{"source":17,"target":15,"value":2},{"source":18,"target":16,"value":2},{"source":18,"target":26,"value":2},{"source":18,"target":3,"value":2},{"source":18,"target":11,"value":2},{"source":18,"target":6,"value":2},{"source":18,"target":25,"value":2},{"source":18,"target":5,"value":2},{"source":19,"target":1,"value":2},{"source":20,"target":5,"value":2},{"source":21,"target":9,"value":2},{"source":22,"target":15,"value":2},{"source":22,"target":25,"value":2},{"source":22,"target":17,"value":2},{"source":23,"target":15,"value":2},{"source":24,"target":11,"value":2},{"source":25,"target":16,"value":2},{"source":25,"target":17,"value":2},{"source":25,"target":5,"value":2},{"source":25,"target":14,"value":2},{"source":26,"target":0,"value":2},{"source":26,"target":6,"value":2},{"source":26,"target":25,"value":2},{"source":26,"target":1,"value":2},{"source":26,"target":18,"value":2}]
}